pangea_openai/__init__.py
pangea_openai/_client.py
pangea_openai/_exceptions.py
pangea_openai/_resource.py
pangea_openai/lib/__init__.py
pangea_openai/lib/azure.py
pangea_openai/py.typed
pangea_openai/resources/responses/__init__.py
pangea_openai/resources/responses/responses.py
pangea_openai-0.2.1.dist-info/WHEEL
pangea_openai-0.2.1.dist-info/METADATA
pangea_openai-0.2.1.dist-info/RECORD
