Metadata-Version: 2.4
Name: pangea-openai
Version: 0.2.1
Summary: A wrapper around the OpenAI Python library that wraps the Responses API with Pangea AI Guard
Author: Pangea
Author-email: Pangea <support@pangea.cloud>
License-Expression: Apache-2.0
Requires-Dist: anyio>=4.11.0
Requires-Dist: httpx>=0.28.1
Requires-Dist: openai>=2.5.0
Requires-Dist: pangea-sdk>=6.7.0
Requires-Dist: pydantic-core>=2.41.4
Requires-Dist: typing-extensions>=4.15.0
Requires-Python: >=3.10
